bom_water/__init__.py
bom_water/_version.py
bom_water/bom_water.py
bom_water/spatial_util.py
bomwater-0.0.8.dist-info/LICENSE
bomwater-0.0.8.dist-info/METADATA
bomwater-0.0.8.dist-info/WHEEL
bomwater-0.0.8.dist-info/top_level.txt
bomwater-0.0.8.dist-info/RECORD
