Metadata-Version: 2.1
Name: bomwater
Version: 0.0.8
Summary: A tool for requesting data from BoM Water Data service.
Home-page: https://github.com/csiro-hydroinformatics/pybomwater
Author: Andrew Freebairn
Author-email: andrew.freebairn@csiro.au
License: UNKNOWN
Platform: UNKNOWN
Classifier: Development Status :: 3 - Alpha
Classifier: Intended Audience :: Science/Research
Classifier: Topic :: Scientific/Engineering :: Hydrology
Classifier: License :: OSI Approved :: BSD License
Classifier: Operating System :: OS Independent
Classifier: Programming Language :: Python
Classifier: Programming Language :: Python :: 3.6
Classifier: Programming Language :: Python :: 3.7
Requires-Dist: requests
Requires-Dist: iso8601
Requires-Dist: pytz
Requires-Dist: json5
Requires-Dist: xmltodict
Requires-Dist: pandas
Requires-Dist: geojson
Requires-Dist: shapely
